mpy_cross_v6_3-1.1.1.data/platlib/mpy_cross_v6_3/__init__.py
mpy_cross_v6_3-1.1.1.data/platlib/mpy_cross_v6_3/__main__.py
mpy_cross_v6_3-1.1.1.data/platlib/mpy_cross_v6_3/mpy-cross
mpy_cross_v6_3-1.1.1.data/platlib/mpy_cross_v6_3/py.typed
mpy_cross_v6_3-1.1.1.dist-info/METADATA
mpy_cross_v6_3-1.1.1.dist-info/WHEEL
mpy_cross_v6_3-1.1.1.dist-info/entry_points.txt
mpy_cross_v6_3-1.1.1.dist-info/top_level.txt
mpy_cross_v6_3-1.1.1.dist-info/RECORD
